buckettree/.bucket_tree.py.swp
buckettree/__init__.py
buckettree/bucket_tree.py
buckettree/test_bucket_tree.py
buckettree/viewer.py
bucket_tree-0.1.4.dist-info/METADATA
bucket_tree-0.1.4.dist-info/WHEEL
bucket_tree-0.1.4.dist-info/licenses/LICENSE
bucket_tree-0.1.4.dist-info/RECORD
