Metadata-Version: 2.4
Name: bucket-tree
Version: 0.1.4
Summary: An online hierarchical binning algorithm
Project-URL: README, https://codeberg.org/brohrer/bucket-tree/src/branch/main/README.md
Project-URL: Repository, https://codeberg.org/brohrer/bucket-tree.git
Author-email: Brandon Rohrer <brohrer@gmail.com>
License-File: LICENSE
Classifier: License :: OSI Approved :: MIT License
Classifier: Operating System :: OS Independent
Classifier: Programming Language :: Python :: 3
Requires-Python: >=3.12
Requires-Dist: numpy
